README.md
setup.py
aiomail/__init__.py
aiomail/email.py
aiomail.egg-info/PKG-INFO
aiomail.egg-info/SOURCES.txt
aiomail.egg-info/dependency_links.txt
aiomail.egg-info/requires.txt
aiomail.egg-info/top_level.txt